atctl/__init__.py
atctl/common.py
atctl/main.py
atctl/scripts/__init__.py
atctl/scripts/root.py
atctl/templates/__init__.py
atctl/templates/case_template.py
atctl/templates/project.py
atctl/utils/__init__.py
atctl/utils/case.py
atctl/utils/template.py
atctl-0.1.4.dist-info/METADATA
atctl-0.1.4.dist-info/WHEEL
atctl-0.1.4.dist-info/entry_points.txt
atctl-0.1.4.dist-info/top_level.txt
atctl-0.1.4.dist-info/RECORD
